{
    "PageTitle": "display link-heartbeat interface",
    "FuncDef": "The display link-heartbeat interface command displays information about link-heartbeat detection on a specified interface.",
    "CLIs": [
        "display link-heartbeat interface { <interface-type> <interface-num> | <interface-name> }"
    ],
    "ParentView": [
        "All views"
    ],
    "ParaDef": [
        {
            "Parameters": "interface-type",
            "Info": "Interface type.\n-"
        },
        {
            "Parameters": "interface-num",
            "Info": "Interface number.\n-"
        },
        {
            "Parameters": "interface-name",
            "Info": "Interface name.\n-"
        }
    ],
    "Examples": [
        [
            "<HUAWEI> display link-heartbeat interface GigabitEthernet 1/0/3",
            " Detecting port      : GigabitEthernet1/0/3.3 ",
            " Send packet port    : GigabitEthernet1/0/3 ",
            " Is trunk member     : False                                                                                                        ",
            " Link-detect Status  : Normal(1)                                                                                                    ",
            " Port ready          : Ready(None)                                                                                                  ",
            " Port avaliable      : Available                                                                                                    ",
            " Port acl download   : Download(2)                                                                                                  ",
            " Lost packet alarm   : Normal                                                                                                       ",
            " Error packet alarm  : Normal                                                                                                       ",
            " IP address          : 192.168.4.2                                                                                                  ",
            " Source MAC          : 00e0-fc48-906a                                                                                               ",
            " Destination MAC     : 00e0-fce3-bdd1                                                                                               ",
            " Port mtu            : 1500                                                                                                         ",
            " Send packet length  : 64   64   255  255  512  512  1023 1023 1500 1500 1200 1200                                                  ",
            " Magic word          : 79** 6a** bc** 6a** 2d** 6a** c9** f0** fe** 02** f8** 80**                                                  ",
            " Feature Flag        : 0    255  0    255  0    255  0    90   0    255  0    255                                                   ",
            " Cyc times           : 0 (for current status)                                                                                       ",
            " Cyc run time(s)     : 17 (for current cycle)                                                                                       ",
            " Cyc template send   : 2    2    2    2    2    2    1    0    0    0    2    2                                                     ",
            " Arp detect info     : 0(no arp flag)  0(arp diagnose flag)                                                                         ",
            " Lost packet info    : 0x00(lost packet flag)  0x00(lost packet diagnose flag)                                                      ",
            " Error packet info   : 0x00(error packet flag)  0x00(error packet diagnose flag)                                                    ",
            " Diagnose packet no  : 255                                                                                                          ",
            " Diagnose times      : 0                                                                                                            ",
            " Diagnose timeout    : 0                                                                                                            ",
            " =====Counter Information=====                                                                                                      ",
            " No arp counter  : 0                                                                                                                ",
            " -----Normal status counter-----                                                                                                    ",
            " Total send      : 17                                                                                                               ",
            " Total receive   : 17                                                                                                               ",
            " Template send   : 2  2  2  2  2  2  1  0  0  0  2  2                                                                               ",
            " Template receive: 2  2  2  2  2  2  1  0  0  0  2  2                                                                               ",
            " Template error  : 0  0  0  0  0  0  0  0  0  0  0  0                                                                               ",
            " -----Approach status counter-----                                                                                                  ",
            " Total send      : 0                                                                                                                ",
            " Total receive   : 0                                                                                                                ",
            " Template send   : 0  0  0  0  0  0  0  0  0  0  0  0                                                                               ",
            " Template receive: 0  0  0  0  0  0  0  0  0  0  0  0                                                                               ",
            " Template error  : 0  0  0  0  0  0  0  0  0  0  0  0                                                                               ",
            " Sub cyc0 error  : 0  0  0  0  0  0  0  0  0  0  0  0                                                                               ",
            " Sub cyc1 error  : 0  0  0  0  0  0  0  0  0  0  0  0                                                                               ",
            " Sub cyc2 error  : 0  0  0  0  0  0  0  0  0  0  0  0                                                                               ",
            " Sub cyc3 error  : 0  0  0  0  0  0  0  0  0  0  0  0                                                                               ",
            " Sub cyc4 error  : 0  0  0  0  0  0  0  0  0  0  0  0                                                                               ",
            " -----Diagnose status counter-----                                                                                                  ",
            " Total send      : 0                                                                                                                ",
            " Total receive   : 0                                                                                                                ",
            " Template send   : 0  0  0  0  0  0  0  0  0  0  0  0                                                                               ",
            " Template receive: 0  0  0  0  0  0  0  0  0  0  0  0                                                                               ",
            " Template error  : 0  0  0  0  0  0  0  0  0  0  0  0                                                                               ",
            " -----All status total counter-----                                                                                                 ",
            " Total send      : 5153                                                                                                             ",
            " Total receive   : 5153                                                                                                             ",
            " Template send   : 174  174  174  174  174  174  173  172  172  172  174  174                                                       ",
            " Template receive: 174  174  174  174  174  174  173  172  172  172  174  174                                                       ",
            " Template error  : 0  0  0  0  0  0  0  0  0  0  0  0"
        ],
        [
            "<HUAWEI> display link-heartbeat interface Eth-Trunk20",
            " Detecting port      : Eth-Trunk20                                                                                                  ",
            " Detect member port  : GigabitEthernet1/0/2                                                                                         ",
            " Trunk id            : 0                                                                                                            ",
            " Link-detect Status  : Approach(2)                                                                                                  ",
            " Port ready          : Ready(None)                                                                                                  ",
            " Port avaliable      : Available                                                                                                    ",
            " Port acl download   : Not download(0)                                                                                              ",
            " Lost packet alarm   : Normal                                                                                                       ",
            " Error packet alarm  : Normal                                                                                                       ",
            " IP address          : 192.168.4.1                                                                                                    ",
            " Source MAC          : 00e0-fcad-4d35                                                                                               ",
            " Destination MAC     : 00e0-fcb0-6ee9                                                                                               ",
            " Port mtu            : 1500                                                                                                         ",
            " Send packet length  : 64    64    255    255    512    512    1023    1023    1500    1500    1500    1500                         ",
            " Magic word          : 79** ae** a3** 4b** ef** 51** f2** f0** 18** 56** de** a4**                                                  ",
            " Feature Flag        : 0    255    0    255    0    255    0    90    0    255    0    255                                          ",
            " Cyc times           : 0 (for current status)                                                                                       ",
            " Cyc run time(s)     : 0 (for current cycle)                                                                                        ",
            " Arp detect info     : 0(no arp flag)  0(arp diagnose flag)                                                                         ",
            " Lost packet info    : 0x00(lost packet flag)  0x00(lost packet diagnose flag)                                                      ",
            " Error packet info   : 0x00(error packet flag)  0x00(error packet diagnose flag)                                                    ",
            " Diagnose packet no  : 255                                                                                                          ",
            " Diagnose times      : 0                                                                                                            ",
            " Diagnose timeout    : 0                                                                                                            ",
            " =====Counter Information=====                                                                                                      ",
            " No arp counter  : 0                                                                                                                ",
            " -----Normal status counter-----                                                                                                    ",
            " Total send      : 24                                                                                                               ",
            " Total receive   : 24                                                                                                               ",
            " Template send   : 2  2  2  2  2  2  2  2  2  2  2  2                                                                               ",
            " Template receive: 2  2  2  2  2  2  2  2  2  2  2  2                                                                               ",
            " Template error  : 2  2  2  0  0  0  0  0  0  0  2  2                                                                               ",
            " -----Approach status counter-----                                                                                                  ",
            " Total send      : 0                                                                                                                ",
            " Total receive   : 0                                                                                                                ",
            " Template send   : 0  0  0  0  0  0  0  0  0  0  0  0                                                                               ",
            " Template receive: 0  0  0  0  0  0  0  0  0  0  0  0                                                                               ",
            " Template error  : 0  0  0  0  0  0  0  0  0  0  0  0                                                                               ",
            " Sub cyc0 error  : 0  0  0  0  0  0  0  0  0  0  0  0                                                                               ",
            " Sub cyc1 error  : 0  0  0  0  0  0  0  0  0  0  0  0                                                                               ",
            " Sub cyc2 error  : 0  0  0  0  0  0  0  0  0  0  0  0                                                                               ",
            " Sub cyc3 error  : 0  0  0  0  0  0  0  0  0  0  0  0                                                                               ",
            " Sub cyc4 error  : 0  0  0  0  0  0  0  0  0  0  0  0                                                                               ",
            " -----Diagnose status counter-----                                                                                                  ",
            " Total send      : 0                                                                                                                ",
            " Total receive   : 0                                                                                                                ",
            " Template send   : 0  0  0  0  0  0  0  0  0  0  0  0                                                                               ",
            " Template receive: 0  0  0  0  0  0  0  0  0  0  0  0                                                                               ",
            " Template error  : 0  0  0  0  0  0  0  0  0  0  0  0                                                                               ",
            " -----All status total counter-----                                                                                                 ",
            " Total send      : 0                                                                                                                ",
            " Total receive   : 0                                                                                                                ",
            " Template send   : 0  0  0  0  0  0  0  0  0  0  0  0                                                                               ",
            " Template receive: 0  0  0  0  0  0  0  0  0  0  0  0                                                                               ",
            " Template error  : 0  0  0  0  0  0  0  0  0  0  0  0"
        ]
    ],
    "ExtraInfo": "Usage Scenario\nAfter link-heartbeat detection is enabled, run the display link-heartbeat command to check packet loss and modification information when link-heartbeat detection is performed on a specified interface and check whether a packet loss or modification alarm is generated.\nPrecautions\nA switch is between two routers, and the routers do not send or detect inter-device heartbeat packets. The routers cannot use the SAID ping or trunk detection functions to detect nodes. As a result, the router resilience function fails."
}