{
    "PageTitle": "display default-parameter mpls te cspf",
    "FuncDef": "The display default-parameter mpls te cspf command displays the default Constraint Shortest Path First (CSPF) parameters and preferred Interior Gateway Protocol (IGP) type.",
    "CLIs": [
        "display default-parameter mpls te cspf"
    ],
    "ParentView": [
        "All views"
    ],
    "ParaDef": null,
    "Examples": [
        [
            "<HUAWEI> display default-parameter mpls te cspf",
            "-----------------------------------------------",
            "          CSPF Default Configuration",
            "-----------------------------------------------",
            "          Preferred-IGP : OSPF",
            "          Failed-link Interval(Sec): 10"
        ]
    ],
    "ExtraInfo": "Usage Scenario\nA CSPF configuration can set a preferred IGP, either Intermediate System-to-Intermediate System (IS-IS) or Open Shortest Path First (OSPF). The default IGP type is OSPF. The display default-parameter mpls te cspf command displays the preferred IGP type."
}