{
    "PageTitle": "ip-mtu",
    "FuncDef": "This command specifies the maximum size of IP packets on this group interface. Packets larger than this are fragmented.",
    "CLIs": [
        "ip-mtu <octets>",
        "no ip-mtu"
    ],
    "ParentView": [
        "config>service>ies>if",
        "config>service>vprn>if"
    ],
    "ParaDef": [
        {
            "Parameters": "octets",
            "Info": "Specifies the largest frame size (in octets) that this interface can handle. Values-512 to 9000."
        }
    ],
    "Examples": null,
    "ExtraInfo": ""
}