{
    "PageTitle": "refresh bgp evpn (IPv6)",
    "FuncDef": "The refresh bgp evpn command configures soft reset for BGP EVPN connections.",
    "CLIs": [
        "refresh bgp evpn <peer-address> { import | export }"
    ],
    "ParentView": [
        "User view"
    ],
    "ParaDef": [
        {
            "Parameters": "peer-address",
            "Info": "Specifies the IPv6 address of a peer.\nThe prefix is a 32-digit hexadecimal number, in the format of X:X:X:X:X:X:X:X."
        },
        {
            "Parameters": "import",
            "Info": "Softly resets BGP EVPN connections in the inbound direction.\n-"
        },
        {
            "Parameters": "export",
            "Info": "Softly resets BGP EVPN connections in the outbound direction.\n-"
        }
    ],
    "Examples": [
        [
            "<HUAWEI> refresh bgp evpn 2001:db8:1::1 import"
        ]
    ],
    "ExtraInfo": "Usage Scenario\nTo softly reset BGP EVPN connections, run the refresh bgp evpn command. BGP EVPN soft reset allows the system to refresh a BGP EVPN routing table without tearing down the BGP EVPN connections and to apply a new filtering policy."
}