{
    "PageTitle": "location",
    "FuncDef": "This command creates a text string that identifies the system location for the device.",
    "CLIs": [
        "location <location>",
        "no location"
    ],
    "ParentView": [
        "config>system"
    ],
    "ParaDef": [
        {
            "Parameters": "location",
            "Info": "Specifies the location as a character string. The string may be up to 80 characters. Any printable, seven-bit ASCII characters can be used within the string. If the string contains special characters (#, $, spaces, etc.), the entire string must be enclosed within double quotes."
        }
    ],
    "Examples": null,
    "ExtraInfo": ""
}