{
    "PageTitle": "transform",
    "FuncDef": "This command configures IPsec transform.",
    "CLIs": [
        "transform <transform-id> [ <transform-id> ]",
        "no transform"
    ],
    "ParentView": [
        "config>ipsec>tnl-temp",
        "config>service>ies>if>sap>ipsec-gw",
        "config>service>vprn>if>sap>ipsec-gw",
        "config>service>vprn>if>sap>ipsec-tunnel"
    ],
    "ParaDef": [
        {
            "Parameters": "transform-id",
            "Info": "Specifies up to four transform IDs."
        }
    ],
    "Examples": null,
    "ExtraInfo": "Default: no transform"
}