{
    "PageTitle": "circuit-id",
    "FuncDef": "This command specifies a circuit-id for PPPoE hosts. A circuit ID received in PPPoE tags has precedence over the LUDB specified circuit ID.",
    "CLIs": [
        "circuit-id sap-id",
        "circuit-id string <ASCII> string",
        "no circuit-id"
    ],
    "ParentView": [
        "config>subscr-mgmt>loc-user-db>ppp>host>ali"
    ],
    "ParaDef": [
        {
            "Parameters": "sap-id",
            "Info": "Specifies to use the SAP ID of the PPPoE session as the circuit ID."
        },
        {
            "Parameters": "ASCII string",
            "Info": "Specifies the circuit ID as a string, up to 63 characters."
        }
    ],
    "Examples": null,
    "ExtraInfo": ""
}