{
    "PageTitle": "qos link-adjustment remote enable",
    "FuncDef": "The qos link-adjustment remote enable command enables the last-mile QoS function.\nThe undo qos link-adjustment remote enable command disables the last-mile QoS function.\nBy default, the last-mile QoS function is disabled.",
    "CLIs": [
        "qos link-adjustment remote enable",
        "undo qos link-adjustment remote enable"
    ],
    "ParentView": [
        "AAA domain view"
    ],
    "ParaDef": null,
    "Examples": [
        [
            "<HUAWEI> system-view",
            "[~HUAWEI] aaa",
            "[~HUAWEI-aaa] domain huawei",
            "[*HUAWEI-aaa-domain-huawei] qos link-adjustment remote enable"
        ]
    ],
    "ExtraInfo": "Usage Scenario\nYou can configure the last-mile QoS function (remote packet adjustment value) only after enabling the last-mile QoS by running the qos link-adjustment remote enable command.\nIf the qos link-adjustment remote enable command is configured in the AAA domain view, the last-mile QoS function takes effect on only L2TP services.\nPrecautions\nIn VS mode, this command is supported only by the admin VS."
}