{
    "PageTitle": "rapid-retry-limit",
    "FuncDef": "This command configures the value of the Rapid Retry Limit. This is used in the retransmission mechanism based on an exponential backoff timer in order to handle unacknowledged message_id objects. The RSVP message with the same message_id is retransmitted every 2 * rapid-retransmit-time interval of time. The node will stop retransmission of unacknowledged RSVP messages whenever the updated backoff interval exceeds the value of the regular refresh interval, or the number of retransmissions reaches the value of therapid-retry-limitparameter, whichever comes first.",
    "CLIs": [
        "rapid-retry-limit <limit>",
        "no rapid-retry-limit"
    ],
    "ParentView": [
        "config>router>gmpls"
    ],
    "ParaDef": [
        {
            "Parameters": "limit",
            "Info": "Specifies the rapid retry limit. Values-1 to 6."
        }
    ],
    "Examples": null,
    "ExtraInfo": "Default: rapid-retry-limit 3"
}