{
    "PageTitle": "reachable-time",
    "FuncDef": "This command configures how long this router should be considered reachable by other nodes on the link after receiving a reachability confirmation.",
    "CLIs": [
        "reachable-time <milli-seconds>",
        "no reachable-time"
    ],
    "ParentView": [
        "config>router>router-advert>if"
    ],
    "ParaDef": [
        {
            "Parameters": "milli-seconds",
            "Info": "Specifies the length of time the router should be considered reachable. Values-0 to 3600000."
        }
    ],
    "Examples": null,
    "ExtraInfo": "Default: no reachable-time"
}