{
    "PageTitle": "display license resource usage rtu-extend-information",
    "FuncDef": "The display license resource usage rtu-extend-information command displays information about the RTU license authorization in cloud mode.",
    "CLIs": [
        "display license resource usage rtu-extend-information { <featurename> | all }"
    ],
    "ParentView": [
        "All views"
    ],
    "ParaDef": [
        {
            "Parameters": "featurename",
            "Info": "Control item.\nThe value is a string of 1 to 31 case-sensitive characters, spaces not supported."
        },
        {
            "Parameters": "all",
            "Info": "All item.\n-"
        }
    ],
    "Examples": [
        [
            "<HUAWEI> display license resource  usage rtu-extend-information  all",
            "FeatureName Descriptions:",
            "====================================================================================",
            "FeatureName            Description                                   Binding Total  ",
            "------------------------------------------------------------------------------------",
            "LCR5*********          **** 10G Port Enable RTU(per 10G)     1       10     ",
            "",
            "Brief RTU Information:",
            "====================================================================================",
            "BarCode                    Allocated       Activated       Available       Total    ",
            "------------------------------------------------------------------------------------",
            "032D********0000           0               1               0               1        ",
            "",
            "Detailed RTU Information:",
            "====================================================================================",
            "BarCode:    032D********0000",
            "------------------------------------------------------------------------------------",
            "Physical Position         Needed Count    Used Count      Active Status             ",
            "------------------------------------------------------------------------------------",
            "5/1/0                     1               0               No allocated              ",
            "5/1/1                     1               1               Activated                 ",
            "5/1/2                     1               0               No allocated              ",
            "5/1/3                     1               0               No allocated              ",
            "5/1/4                     1               0               No allocated              ",
            "5/1/5                     1               0               No allocated              ",
            "5/1/6                     1               0               No allocated              ",
            "5/1/7                     1               0               No allocated              ",
            "5/1/8                     1               0               No allocated              ",
            "5/1/9                     1               0               No allocated              ",
            "5/1/10                    1               0               No allocated              ",
            "5/1/11                    1               0               No allocated              ",
            "5/1/12                    1               0               No allocated              ",
            "5/1/13                    1               0               No allocated              ",
            "5/1/14                    1               0               No allocated              ",
            "5/1/15                    1               0               No allocated              ",
            "5/1/16                    1               0               No allocated              ",
            "5/1/17                    1               0               No allocated              ",
            "5/1/18                    1               0               No allocated              ",
            "5/1/19                    1               0               No allocated              ",
            "",
            "************************************************************************************"
        ]
    ],
    "ExtraInfo": "Usage Scenario\nTo check information about the RTU license authorization in cloud mode, run the display license resource usage rtu-extend-information command."
}