{
    "PageTitle": "symbol-monitor",
    "FuncDef": "This command configures Ethernet Symbol Monitoring parameters. Support for symbol monitoring is hardware dependent. An error message indicating that the port setting cannot be modified will be presented when attempting to enable the feature or configure the individual parameters on unsupported hardware.",
    "CLIs": [
        "symbol-monitor"
    ],
    "ParentView": [
        "config>port>ethernet"
    ],
    "ParaDef": null,
    "Examples": null,
    "ExtraInfo": ""
}