{
    "PageTitle": "user enable",
    "FuncDef": "The user enable command activates aged users.",
    "CLIs": [
        "user <user-name> enable"
    ],
    "ParentView": [
        "Local AAA server view"
    ],
    "ParaDef": [
        {
            "Parameters": "user-name",
            "Info": "Specifies the aged user name to be activated.\nThe value is a string of 1 to 253 case-insensitive characters without spaces. If the value includes @, the characters before @ are the user name and the characters after @ are the domain name. If the value excludes @ or the domain name does not exist, the entire string is the user name and the user belongs to the default domain. A user name cannot contain two or more @s."
        }
    ],
    "Examples": [
        [
            "<HUAWEI> system-view",
            "[~HUAWEI] local-aaa-server",
            "[*HUAWEI-local-aaa-server] user user13579 password cipher 1qaz@WSX",
            "[~HUAWEI-local-aaa-server] user user13579 enable"
        ]
    ],
    "ExtraInfo": "Usage Scenario\nAfter the user-aging command is run, if the aging period expires, users are aged and cannot log in. To activate the aged users, you can run the user enable command.\nAfter this command is run, if users are not aged, the aging period will be refreshed."
}