{
    "PageTitle": "i-counters",
    "FuncDef": "This command configures ingress counter parameters for this custom record.",
    "CLIs": [
        "i-counters [ all ]",
        "no i-counters"
    ],
    "ParentView": [
        "config>log>acct-policy>cr>override-cntr",
        "config>log>acct-policy>cr>queue",
        "config>log>acct-policy>cr>ref-override-cntr",
        "config>log>acct-policy>cr>ref-queue"
    ],
    "ParaDef": [
        {
            "Parameters": "all",
            "Info": "Specifies all ingress counters should be included."
        }
    ],
    "Examples": null,
    "ExtraInfo": ""
}