{
    "PageTitle": "primary-dns",
    "FuncDef": "This command configures the primary DNS server used for DNS name resolution. DNS name resolution can be used when executing ping, traceroute, and service-ping, and also when defining file URLs. DNS name resolution is not supported when DNS names are embedded in configuration files.",
    "CLIs": [
        "primary-dns <ip-address>",
        "no primary-dns"
    ],
    "ParentView": [
        "config>service>vprn>dns"
    ],
    "ParaDef": [
        {
            "Parameters": "ip-address",
            "Info": "The IP or IPv6 address of the primary DNS server."
        }
    ],
    "Examples": null,
    "ExtraInfo": "Default: no primary-dns - No primary DNS server is configured."
}