{
    "PageTitle": "slm",
    "FuncDef": "This command defines the test ID to be assigned to the synthetic loss test and creates the container to allow the individual test parameters to be configured.",
    "CLIs": [
        "slm [ test-id <test-id> ] [ create ]",
        "no slm"
    ],
    "ParentView": [
        "config>oam-pm>session>ethernet"
    ],
    "ParaDef": [
        {
            "Parameters": "test-id",
            "Info": "Specifies the value to be placed in the 4-byte test ID field of an ETH-SLM PDU. Values-0 to 2147483647."
        },
        {
            "Parameters": "create",
            "Info": "Keyword to create the test."
        }
    ],
    "Examples": null,
    "ExtraInfo": ""
}