{
    "PageTitle": "ssl verify-mode",
    "FuncDef": "The ssl verify-mode command configures the DCN Secure Sockets Layer (SSL) authentication mode.\nBy default, the DCN SSL authentication mode is single.",
    "CLIs": [
        "ssl verify-mode single",
        "ssl verify-mode dual",
        "undo ssl verify-mode"
    ],
    "ParentView": [
        "DCN view"
    ],
    "ParaDef": [
        {
            "Parameters": "dual",
            "Info": "Specifies the dual authentication mode.\n-"
        },
        {
            "Parameters": "single",
            "Info": "Specifies the single authentication mode.\n-"
        }
    ],
    "Examples": [
        [
            "<HUAWEI> system-view",
            "[~HUAWEI] dcn",
            "[*HUAWEI-dcn] set compatible mode",
            "[*HUAWEI-dcn] ssl verify-mode dual"
        ]
    ],
    "ExtraInfo": "Usage Scenario\nIn singe mode, SSL authentication is performed only on the GNE. In dual mode, SSL authentications are performed both on the GNE and NMS.\nIt is recommended that you configure the dual authentication mode to enhance system security.\nPrerequisites\nThe DCN feature has been enabled globally using the dcn command in the system view.\nThe certificate of the SSL policy to be bound has been loaded to the NMSs and GNE using the certificate load command. The SSL policy has been configured using the ssl policy command.\nRun the set compatible mode command to enable the DCN compatible mode\nPrecautions\nIn VS mode, this command is supported only by the admin VS."
}