{
    "PageTitle": "p2mp-s2l-fast-retry",
    "FuncDef": "This command configures a global parameter to allow the user to apply a shorter retry timer for the first try after an active LSP path went down due to a local failure or the receipt of a ResvTear. This timer is used only in the first try. Subsequent retries will continue to be governed by the existing LSP level retry-timer.",
    "CLIs": [
        "p2mp-s2-fast-retry <seconds>",
        "no p2mp-s2l-fast-retry"
    ],
    "ParentView": [
        "config>router>mpls",
        "config>router>rsvp"
    ],
    "ParaDef": [
        {
            "Parameters": "seconds",
            "Info": "Specifies the length of time for retry timer, in seconds. Values-1 to 10 seconds."
        }
    ],
    "Examples": null,
    "ExtraInfo": "Default: no p2mp-s2l-fast-retry"
}