{
    "PageTitle": "mac-list",
    "FuncDef": "This command associates a previously created MAC list to a dynamic IP. The MAC list is created using theconfig>service>proxy-arp-nd>mac-listcommand.",
    "CLIs": [
        "mac-list <name>",
        "no mac-list"
    ],
    "ParentView": [
        "config>service>vpls>proxy-arp>dynamic",
        "config>service>vpls>proxy-nd>dynamic"
    ],
    "ParaDef": [
        {
            "Parameters": "name",
            "Info": "The name of the MAC list previously created using the config>service>proxy-arp-nd>mac-list command."
        }
    ],
    "Examples": null,
    "ExtraInfo": ""
}